vidgen/__init__.py
vidgen/console.py
vidgen/reddit.py
vidgen-0.2.0.dist-info/entry_points.txt
vidgen-0.2.0.dist-info/LICENSE
vidgen-0.2.0.dist-info/WHEEL
vidgen-0.2.0.dist-info/METADATA
vidgen-0.2.0.dist-info/RECORD
