Metadata-Version: 2.1
Name: vidgen
Version: 0.2.0
Summary: Automatic video generation
License: MIT
Author: Your Name
Author-email: you@example.com
Requires-Python: >=3.7,<4.0
Classifier: License :: OSI Approved :: MIT License
Classifier: Programming Language :: Python :: 3
Classifier: Programming Language :: Python :: 3.7
Classifier: Programming Language :: Python :: 3.8
Requires-Dist: click (>=7.1.2,<8.0.0)
Requires-Dist: importlib_metadata (>=1.6.0,<2.0.0); python_version < "3.8"
Requires-Dist: praw (>=7.0.0,<8.0.0)
Requires-Dist: requests (>=2.23.0,<3.0.0)
